{
  "type": "MaxHistoryTrackerFeaturizer",
  "state_featurizer": {
    "action_texts": [],
    "entity_tag_specs": [],
    "feature_states": {
      "intent": {
        "ask_discounts": 0,
        "ask_hours": 1,
        "ask_location": 2,
        "ask_menu": 3,
        "back": 4,
        "delivery_options": 5,
        "goodbye": 6,
        "greet": 7,
        "nlu_fallback": 8,
        "out_of_scope": 9,
        "payment_methods": 10,
        "provide_issue": 11,
        "provide_order_number": 12,
        "report_issue": 13,
        "restart": 14,
        "session_start": 15,
        "thank": 16,
        "track_order": 17
      },
      "action_name": {
        "action_listen": 0,
        "action_restart": 1,
        "action_session_start": 2,
        "action_default_fallback": 3,
        "action_deactivate_loop": 4,
        "action_revert_fallback_events": 5,
        "action_default_ask_affirmation": 6,
        "action_default_ask_rephrase": 7,
        "action_two_stage_fallback": 8,
        "action_unlikely_intent": 9,
        "action_back": 10,
        "...": 11,
        "action_extract_slots": 12,
        "handle_information_queries": 13,
        "handle_menu_queries": 14,
        "handle_track_order": 15,
        "handle_report_issue": 16,
        "utter_ask_contact_method": 17,
        "utter_ask_issue": 18,
        "utter_ask_order_number": 19,
        "utter_goodbye": 20,
        "utter_greet": 21,
        "utter_thank": 22
      },
      "entities": {
        "contact_method": 0,
        "issue": 1,
        "order_number": 2
      },
      "slots": {},
      "active_loop": {}
    }
  },
  "remove_duplicates": true,
  "max_history": 5
}